containup/__init__.py
containup/containup_cli.py
containup/containup_run.py
containup/healthcheck_helpers.py
containup/business/__init__.py
containup/business/audit/__init__.py
containup/business/audit/audit_alert.py
containup/business/audit/audit_container_image.py
containup/business/audit/audit_depends_on.py
containup/business/audit/audit_registry.py
containup/business/audit/audit_report.py
containup/business/audit/audit_secrets.py
containup/business/audit/audit_service_healthcheck.py
containup/business/audit/audit_service_mounts.py
containup/business/commands/__init__.py
containup/business/commands/command_down.py
containup/business/commands/command_up.py
containup/business/commands/container_health_status.py
containup/business/commands/container_operator.py
containup/business/commands/user_interactions.py
containup/business/execution_listener/__init__.py
containup/business/healhcheck_helpers/__init__.py
containup/business/live_state/__init__.py
containup/business/live_state/stack_state.py
containup/business/live_state/stack_state_resolver.py
containup/business/plugins/plugin_builtins.py
containup/business/plugins/plugin_registry.py
containup/business/reports/report_generator.py
containup/business/reports/report_standard.py
containup/infra/__init__.py
containup/infra/user_interactions_cli.py
containup/infra/docker/__init__.py
containup/infra/docker/docker_operator.py
containup/infra/docker/healthcheck.py
containup/infra/docker/mounts.py
containup/infra/docker/ports.py
containup/infra/dryrun/dryrun_operator.py
containup/infra/runner/__init__.py
containup/infra/runner/runner.py
containup/stack/__init__.py
containup/stack/network.py
containup/stack/service.py
containup/stack/service_healthcheck.py
containup/stack/service_mounts.py
containup/stack/service_ports.py
containup/stack/stack.py
containup/stack/volume.py
containup/utils/__init__.py
containup/utils/absolute_paths.py
containup/utils/duration_to_nano.py
containup/utils/secret_value.py
containup-0.1.10.dist-info/licenses/LICENSE
containup-0.1.10.dist-info/METADATA
containup-0.1.10.dist-info/WHEEL
containup-0.1.10.dist-info/top_level.txt
containup-0.1.10.dist-info/RECORD
