Metadata-Version: 2.4
Name: containup
Version: 0.1.10
Summary: Define Docker stacks in Python, include your environments logic, extend as you wish, no YAML.
Author: Sébastien JUST
License-Expression: GPL-3.0-or-later
Project-URL: Homepage, https://github.com/sebastienjust/containup-py
Project-URL: Repository, https://github.com/sebastienjust/containup-py.git
Project-URL: Issues, https://github.com/sebastienjust/containup-py/issues
Project-URL: Changelog, https://github.com/sebastienjust/containup-py/blob/main/CHANGELOG.md
Keywords: docker,compose,docker-compose,containers,infrastructure,orchestration,stack,devops,deployment,python,automation
Classifier: Development Status :: 3 - Alpha
Classifier: Environment :: Console
Classifier: Intended Audience :: Developers
Classifier: Topic :: System :: Systems Administration
Classifier: Topic :: System :: Software Distribution
Classifier: Topic :: Software Development :: Build Tools
Classifier: Programming Language :: Python :: 3
Classifier: Programming Language :: Python :: 3.9
Classifier: Operating System :: OS Independent
Requires-Python: >=3.9
License-File: LICENSE
Requires-Dist: docker==7.1.0
Requires-Dist: typing_extensions==4.13.2
Dynamic: license-file
